{
   "branch-conditions-v": {
      "i": 2, 
      "i<i": 1, 
      "i>=i": 1
   }, 
   "method-assignments-v": {
      "((((b[i] & 255) | ((b[(i + 1)] & 255) << 8)) | ((b[(i + 2)] & 255) << 16)) | ((b[(i + 3)] & 255) << 24))": 1, 
      "(((b[i] & 255) | ((b[(i + 1)] & 255) << 8)) | ((b[(i + 2)] & 255) << 16))": 1, 
      "((b[(i + 1)] & 255) << 8)": 2, 
      "((b[(i + 2)] & 255) << 16)": 2, 
      "((b[(i + 3)] & 255) << 24)": 1, 
      "((b[i] & 255) | ((b[(i + 1)] & 255) << 8))": 1, 
      "((i * 5) + -430675100)": 1, 
      "(b[(i + 1)] & 255)": 2, 
      "(b[(i + 2)] & 255)": 2, 
      "(b[(i + 3)] & 255)": 1, 
      "(b[i] & 255)": 2, 
      "(i * -1028477387)": 1, 
      "(i * -2048144789)": 1, 
      "(i * -862048943)": 2, 
      "(i * 461845907)": 2, 
      "(i * 5)": 1, 
      "(i + 1)": 2, 
      "(i + 2)": 2, 
      "(i + 3)": 1, 
      "(i >> 13)": 1, 
      "(i >> 16)": 2, 
      "(i ^ ((b[(i + 1)] & 255) << 8))": 1, 
      "(i ^ ((b[(i + 2)] & 255) << 16))": 1, 
      "(i ^ (b[i] & 255))": 1, 
      "(i ^ (i >> 13))": 1, 
      "(i ^ (i >> 16))": 2, 
      "(i ^ i)": 2, 
      "-1028477387": 1, 
      "-2048144789": 1, 
      "-430675100": 1, 
      "-862048943": 3, 
      "13": 2, 
      "15": 2, 
      "16": 4, 
      "24": 1, 
      "255": 7, 
      "3": 1, 
      "4": 2, 
      "4221880213": 1, 
      "461845907": 3, 
      "5": 1, 
      "8": 2, 
      "b": 9, 
      "b[(i + 1)]": 2, 
      "b[(i + 2)]": 2, 
      "b[(i + 3)]": 1, 
      "i": 33, 
      "i += 4": 1, 
      "i:=((((b[i] & 255) | ((b[(i + 1)] & 255) << 8)) | ((b[(i + 2)] & 255) << 16)) | ((b[(i + 3)] & 255) << 24))": 1, 
      "i:=((i * 5) + -430675100)": 1, 
      "i:=(i * -1028477387)": 1, 
      "i:=(i * -2048144789)": 1, 
      "i:=(i * -862048943)": 2, 
      "i:=(i * 461845907)": 2, 
      "i:=(i ^ ((b[(i + 1)] & 255) << 8))": 1, 
      "i:=(i ^ ((b[(i + 2)] & 255) << 16))": 1, 
      "i:=(i ^ (b[i] & 255))": 1, 
      "i:=(i ^ (i >> 13))": 1, 
      "i:=(i ^ (i >> 16))": 2, 
      "i:=(i ^ i)": 2, 
      "i:=-862048943": 1, 
       "i:=461845907": 1
   }, 
   "method-assignments-vmcfs": {
      "((((b[i] & 255) | ((b[(i + 1)] & 255) << 8)) | ((b[(i + 2)] & 255) << 16)) | ((b[(i + 3)] & 255) << 24))": 1, 
      "(((b[i] & 255) | ((b[(i + 1)] & 255) << 8)) | ((b[(i + 2)] & 255) << 16))": 1, 
      "((b[(i + 1)] & 255) << 8)": 2, 
      "((b[(i + 2)] & 255) << 16)": 2, 
      "((b[(i + 3)] & 255) << 24)": 1, 
      "((b[i] & 255) | ((b[(i + 1)] & 255) << 8))": 1, 
      "((i * 5) + -430675100)": 1, 
      "(b[(i + 1)] & 255)": 2, 
      "(b[(i + 2)] & 255)": 2, 
      "(b[(i + 3)] & 255)": 1, 
      "(b[i] & 255)": 2, 
      "(i * -1028477387)": 1, 
      "(i * -2048144789)": 1, 
      "(i * -862048943)": 2, 
      "(i * 461845907)": 2, 
      "(i * 5)": 1, 
      "(i + 1)": 2, 
      "(i + 2)": 2, 
      "(i + 3)": 1, 
      "(i >> 13)": 1, 
      "(i >> 16)": 2, 
      "(i ^ ((b[(i + 1)] & 255) << 8))": 1, 
      "(i ^ ((b[(i + 2)] & 255) << 16))": 1, 
      "(i ^ (b[i] & 255))": 1, 
      "(i ^ (i >> 13))": 1, 
      "(i ^ (i >> 16))": 2, 
      "(i ^ i)": 2, 
      "-1028477387": 1, 
      "-2048144789": 1, 
      "-430675100": 1, 
      "-862048943": 3, 
      "13": 2, 
      "15": 2, 
      "16": 4, 
      "24": 1, 
      "255": 7, 
      "3": 1, 
      "4": 2, 
      "4221880213": 1, 
      "461845907": 3, 
      "5": 1, 
      "8": 2, 
      "b[(i + 1)]": 2, 
      "b[(i + 2)]": 2, 
      "b[(i + 3)]": 1, 
      "b[i]": 2, 
      "i += 4": 1, 
      "i:=((((b[i] & 255) | ((b[(i + 1)] & 255) << 8)) | ((b[(i + 2)] & 255) << 16)) | ((b[(i + 3)] & 255) << 24))": 1, 
      "i:=((i * 5) + -430675100)": 1, 
      "i:=(i * -1028477387)": 1, 
      "i:=(i * -2048144789)": 1, 
      "i:=(i * -862048943)": 2, 
      "i:=(i * 461845907)": 2, 
      "i:=(i ^ ((b[(i + 1)] & 255) << 8))": 1, 
      "i:=(i ^ ((b[(i + 2)] & 255) << 16))": 1, 
      "i:=(i ^ (b[i] & 255))": 1, 
      "i:=(i ^ (i >> 13))": 1, 
      "i:=(i ^ (i >> 16))": 2, 
      "i:=(i ^ i)": 2, 
      "i:=-862048943": 1, 
      "i:=461845907": 1, 
      "i:=C.m(i,13)": 1, 
      "i:=C.m(i,15)": 2
   }, 
   "method-assignments-vmcfsi": {
      "((((b[i] & n) | ((b[(i + 1)] & n) << n)) | ((b[(i + n)] & n) << n)) | ((b[(i + n)] & n) << n))": 1, 
      "(((b[i] & n) | ((b[(i + 1)] & n) << n)) | ((b[(i + n)] & n) << n))": 1, 
      "((b[(i + 1)] & n) << n)": 2, 
      "((b[(i + n)] & n) << n)": 3, 
      "((b[i] & n) | ((b[(i + 1)] & n) << n))": 1, 
      "((i * n) + n)": 1, 
      "(b[(i + 1)] & n)": 2, 
      "(b[(i + n)] & n)": 3, 
      "(b[i] & n)": 2, 
      "(i * n)": 7, 
      "(i + 1)": 2, 
      "(i + n)": 3, 
      "(i >> n)": 3, 
      "(i ^ ((b[(i + 1)] & n) << n))": 1, 
      "(i ^ ((b[(i + n)] & n) << n))": 1, 
      "(i ^ (b[i] & n))": 1, 
      "(i ^ (i >> n))": 3, 
      "(i ^ i)": 2, 
      "b[(i + 1)]": 2, 
      "b[(i + n)]": 3, 
      "i += 4": 1, 
      "i:=((((b[i] & n) | ((b[(i + 1)] & n) << n)) | ((b[(i + n)] & n) << n)) | ((b[(i + n)] & n) << n))": 1, 
      "i:=((i * n) + n)": 1, 
      "i:=(i * n)": 6, 
      "i:=(i ^ ((b[(i + 1)] & n) << n))": 1, 
      "i:=(i ^ ((b[(i + n)] & n) << n))": 1, 
      "i:=(i ^ (b[i] & n))": 1, 
      "i:=(i ^ (i >> n))": 3, 
      "i:=(i ^ i)": 2 
   }, 
   "signatures": {
      "([BJI[B)I": 1
   }, 
   "sizes": {
      "loops": 1
   }
}
